udpscope/__init__.py
udpscope/analyzer.py
udpscope/capture.py
udpscope/cli.py
udpscope/diagnostics.py
udpscope/parser.py
udpscope/py.typed
udpscope/report.py
udpscope/utils.py
udpscope/cmd/__init__.py
udpscope/cmd/udpscope/__init__.py
udpscope/cmd/udpscope/main.py
udpscope-1.0.2.dist-info/licenses/LICENSE
udpscope-1.0.2.dist-info/METADATA
udpscope-1.0.2.dist-info/WHEEL
udpscope-1.0.2.dist-info/entry_points.txt
udpscope-1.0.2.dist-info/top_level.txt
udpscope-1.0.2.dist-info/RECORD
