Metadata-Version: 2.4
Name: udpscope
Version: 1.0.2
Summary: Professional UDP traffic analysis and diagnostics tool
Home-page: https://github.com/najuaircrack/UDPscope
Author: UDPscope Maintainers
Author-email: UDPscope Maintainers <kcnajwan7@gmail.com>
Maintainer-email: UDPscope Team <team@udpscope.org>
License: MIT
Project-URL: Homepage, https://github.com/najuaircrack/UDPscope
Project-URL: Repository, https://github.com/najuaircrack/UDPscope.git
Project-URL: Issues, https://github.com/najuaircrack/UDPscope/issues
Keywords: network,udp,analysis,diagnostics,monitoring
Classifier: Development Status :: 5 - Production/Stable
Classifier: Intended Audience :: System Administrators
Classifier: Operating System :: POSIX :: Linux
Classifier: Programming Language :: Python :: 3
Classifier: Programming Language :: Python :: 3.8
Classifier: Programming Language :: Python :: 3.9
Classifier: Programming Language :: Python :: 3.10
Classifier: Programming Language :: Python :: 3.11
Classifier: Programming Language :: Python :: 3.12
Classifier: Topic :: System :: Networking :: Monitoring
Classifier: Topic :: System :: Systems Administration
Requires-Python: >=3.8
License-File: LICENSE
Requires-Dist: numpy>=1.21.0
Dynamic: license-file
